morastrja/__init__.py
morastrja/__init__.pyi
morastrja/__main__.py
morastrja/_morastr.cp38-win_amd64.pyd
morastrja/utils.py
morastrja/utils.pyi
morastrja/data/__init__.py
morastrja/data/table.bak
morastrja/data/table.py
morastrja-0.8.5.dist-info/METADATA
morastrja-0.8.5.dist-info/WHEEL
morastrja-0.8.5.dist-info/top_level.txt
morastrja-0.8.5.dist-info/RECORD
